sqlitetocsv/__init__.py
sqlitetocsv/csvexport.py
sqlitetocsv-0.1.1.dist-info/LICENSE.txt
sqlitetocsv-0.1.1.dist-info/METADATA
sqlitetocsv-0.1.1.dist-info/WHEEL
sqlitetocsv-0.1.1.dist-info/top_level.txt
sqlitetocsv-0.1.1.dist-info/RECORD
