Metadata-Version: 2.1
Name: sqlitetocsv
Version: 0.1.1
Summary: Useful package to export all the tables from sqlite db to csv files
Home-page: https://github.com/MullionGroup/sqlitetocsv
Author: Kaushik Sangem
Author-email: Kaushik.Sangem@mulliongroup.com
License: MIT
Download-URL: https://pypi.org/project/elastictools/
Keywords: Sqlite,CSV,sqlite to csv,Python 3
Platform: UNKNOWN
Requires-Dist: pandas
